{"assets":{"DAECE3120CAC8261596DE2338F8FA11F":{"type":"texture","index":0,"url":{"native":"assets\/A261BF11-D81C-4D1A-B882-5F0777EEC6CB.pdf"},"width":1920,"height":1080},"46DA90D6B9471D7412CC370A24387B6E":{"type":"texture","index":1,"url":{"native":"assets\/A261BF11-D81C-4D1A-B882-5F0777EEC6CB.pdf"},"width":1920,"height":1080}},"events":[{"effects":[{"beginTime":0,"baseLayer":{"animations":[],"initialState":{"affineTransform":[1,0,0,1,0,0],"masksToBounds":false,"rotation":0,"scale":1,"position":{"pointX":960,"pointY":540},"width":1920,"sublayerTransform":[1,0,0,0,0,1,0,0,0,0,1,0,0,0,0,1],"contentsRect":{"y":0,"x":0,"width":1,"height":1},"opacity":1,"edgeAntialiasingMask":251658240,"height":1080,"hidden":false,"anchorPoint":{"pointX":0.5,"pointY":0.5}},"objectID":"0","layers":[{"animations":[],"initialState":{"affineTransform":[1,0,0,1,0,0],"masksToBounds":false,"rotation":0,"scale":1,"position":{"pointX":960,"pointY":540},"width":1920,"sublayerTransform":[1,0,0,0,0,1,0,0,0,0,1,-0.00035007912466775983,0,0,0,1],"contentsRect":{"y":0,"x":0,"width":1,"height":1},"opacity":1,"edgeAntialiasingMask":251658240,"height":1080,"hidden":false,"anchorPoint":{"pointX":0.5,"pointY":0.5}},"layers":[{"animations":[],"layers":[],"texturedRectangle":{"isBackgroundTexture":false,"singleTextureOpacity":1,"textureType":0,"textBaseline":0,"textXHeight":0,"isVerticalText":false},"initialState":{"affineTransform":[1,0,0,1,0,0],"masksToBounds":false,"rotation":0,"scale":1,"position":{"pointX":960,"pointY":540},"width":1920,"sublayerTransform":[1,0,0,0,0,1,0,0,0,0,1,0,0,0,0,1],"contentsRect":{"y":0,"x":0,"width":1,"height":1},"opacity":1,"edgeAntialiasingMask":0,"height":1080,"hidden":false,"anchorPoint":{"pointX":0.5,"pointY":0.5}},"texture":"46DA90D6B9471D7412CC370A24387B6E"},{"animations":[{"additive":false,"timeOffset":0,"beginTime":0,"from":{"scalar":false},"repeatCount":0,"fillMode":"both","duration":0.001,"autoreverses":false,"property":"hidden","to":{"scalar":true},"removedOnCompletion":false}],"layers":[],"texturedRectangle":{"isBackgroundTexture":false,"singleTextureOpacity":1,"textureType":0,"textBaseline":0,"textXHeight":0,"isVerticalText":false},"initialState":{"affineTransform":[1,0,0,1,0,0],"masksToBounds":false,"rotation":0,"scale":1,"position":{"pointX":960,"pointY":540},"width":1920,"sublayerTransform":[1,0,0,0,0,1,0,0,0,0,1,0,0,0,0,1],"contentsRect":{"y":0,"x":0,"width":1,"height":1},"opacity":1,"edgeAntialiasingMask":0,"height":1080,"hidden":false,"anchorPoint":{"pointX":0.5,"pointY":0.5}},"texture":"DAECE3120CAC8261596DE2338F8FA11F"}]}]},"effects":[],"duration":0.001,"type":"transition","attributes":{"direction":0},"name":"none","objectID":"0"}],"automaticPlay":false,"hyperlinks":[],"accessibility":[{"text":"Kite","targetRectangle":{"y":898.09443593103595,"x":1324.9161987304688,"width":55.950000000000045,"height":29.999987840652466}},{"text":"THEO WENNER","targetRectangle":{"y":1036.3363803625107,"x":1747.5019843381592,"width":142.00199999999995,"height":18.399992704391479}},{"text":"Beyond the Hedgerows","targetRectangle":{"y":34.192079544067383,"x":863.18000000000006,"width":193.63999999999987,"height":19.999991893768311}},{"text":"SET DESIGN","targetRectangle":{"y":58.192079544067383,"x":895.81999999999994,"width":128.36000000000013,"height":19.999991893768311}},{"text":"ac3d3069af733e0f4a0a52217c4d13c0.jpg","targetRectangle":{"y":104.46156287271721,"x":1318.6465942180589,"width":577.18800771272936,"height":781.28125}},{"text":"par116898-teaser-story-big.jpg","targetRectangle":{"y":103.39906292526416,"x":557.91621791507305,"width":744.97686767578125,"height":501.69534301757812}},{"text":"TeePee","targetRectangle":{"y":801.91529774744231,"x":33.916217803955085,"width":85.950000000000017,"height":29.999987840652466}},{"text":"￼","targetRectangle":{"y":1035.5364093780518,"x":950.99997520446777,"width":18,"height":18.399992704391479}},{"text":"See-saw","targetRectangle":{"y":619.09440600963489,"x":561.91621780395508,"width":101.30999999999995,"height":29.999987840652466}},{"text":"2ab3c7b1bc919f0c62dce9765742f5c9.jpg","targetRectangle":{"y":103.39906287271742,"x":30,"width":501.5625,"height":684.91674799999998}},{"text":"LONGCHAMP","targetRectangle":{"y":1036.3363802924227,"x":30.398827774100077,"width":124.90199999999999,"height":18.399992704391479}}],"baseLayer":{"animations":[],"initialState":{"affineTransform":[1,0,0,1,0,0],"masksToBounds":false,"rotation":0,"scale":1,"position":{"pointX":960,"pointY":540},"width":1920,"sublayerTransform":[1,0,0,0,0,1,0,0,0,0,1,0,0,0,0,1],"contentsRect":{"y":0,"x":0,"width":1,"height":1},"opacity":1,"edgeAntialiasingMask":251658240,"height":1080,"hidden":false,"anchorPoint":{"pointX":0.5,"pointY":0.5}},"objectID":"0","layers":[{"animations":[],"initialState":{"affineTransform":[1,0,0,1,0,0],"masksToBounds":false,"rotation":0,"scale":1,"position":{"pointX":960,"pointY":540},"width":1920,"sublayerTransform":[1,0,0,0,0,1,0,0,0,0,1,-0.00035007912466775983,0,0,0,1],"contentsRect":{"y":0,"x":0,"width":1,"height":1},"opacity":1,"edgeAntialiasingMask":251658240,"height":1080,"hidden":false,"anchorPoint":{"pointX":0.5,"pointY":0.5}},"layers":[{"animations":[],"layers":[],"texturedRectangle":{"isBackgroundTexture":false,"singleTextureOpacity":1,"textureType":0,"textBaseline":0,"textXHeight":0,"isVerticalText":false},"initialState":{"affineTransform":[1,0,0,1,0,0],"masksToBounds":false,"rotation":0,"scale":1,"position":{"pointX":960,"pointY":540},"width":1920,"sublayerTransform":[1,0,0,0,0,1,0,0,0,0,1,0,0,0,0,1],"contentsRect":{"y":0,"x":0,"width":1,"height":1},"opacity":1,"edgeAntialiasingMask":0,"height":1080,"hidden":false,"anchorPoint":{"pointX":0.5,"pointY":0.5}},"texture":"DAECE3120CAC8261596DE2338F8FA11F"}]}]}}]}